pygrafanaapi/__init__.py
pygrafanaapi/pygrafanaapi.py
pygrafanaapi-1.0.0.dist-info/LICENSE.txt
pygrafanaapi-1.0.0.dist-info/METADATA
pygrafanaapi-1.0.0.dist-info/WHEEL
pygrafanaapi-1.0.0.dist-info/top_level.txt
pygrafanaapi-1.0.0.dist-info/RECORD
