Metadata-Version: 2.1
Name: pygrafanaapi
Version: 1.0.0
Summary: pygrafanaapi facilitates the usage of grafana apis inside a python module
Home-page: https://github.com/stormalf/grafana_apis
Author: Stormalf
Author-email: stormalf.dev@gmail.com
License: UNKNOWN
Project-URL: Bug Reports, https://github.com/stormalf/grafana_apis/issues
Project-URL: Source, https://github.com/stormalf/grafana_apis/
Keywords: pygrafanaapi
Platform: UNKNOWN
Classifier: Development Status :: 3 - Alpha
Classifier: Intended Audience :: Developers
Classifier: Topic :: Software Development :: Build Tools
Classifier: License :: OSI Approved :: MIT License
Classifier: Programming Language :: Python :: 3
Classifier: Programming Language :: Python :: 3.6
Classifier: Programming Language :: Python :: 3.7
Classifier: Programming Language :: Python :: 3.8
Classifier: Programming Language :: Python :: 3.9
Classifier: Programming Language :: Python :: 3 :: Only
Requires-Python: >=3.6, <4
License-File: LICENSE.txt
Requires-Dist: cryptography
Requires-Dist: requests
